cherrypy_cors/__init__.py
cherrypy_cors-1.7.0.dist-info/LICENSE
cherrypy_cors-1.7.0.dist-info/METADATA
cherrypy_cors-1.7.0.dist-info/WHEEL
cherrypy_cors-1.7.0.dist-info/top_level.txt
cherrypy_cors-1.7.0.dist-info/RECORD
