Metadata-Version: 2.1
Name: cherrypy-cors
Version: 1.7.0
Summary: CORS handling as a cherrypy tool.
Home-page: https://github.com/cherrypy/cherrypy-cors
Author: Jason R. Coombs
Author-email: jaraco@jaraco.com
Classifier: Development Status :: 5 - Production/Stable
Classifier: Intended Audience :: Developers
Classifier: License :: OSI Approved :: MIT License
Classifier: Programming Language :: Python :: 3
Classifier: Programming Language :: Python :: 3 :: Only
Requires-Python: >=3.8
Provides-Extra: testing
Provides-Extra: docs
License-File: LICENSE
